{
"head": {
    "tm": "62580",
    "side": "1",
    "noRom": "0",
    "part": "H",
    "graphicURL": "http://berlpap.smb.museum/Original/P_09782-Pl-H_R_001.jpg",
    "graphicName": "62580_42-52__PBerol9782_Pl_H_R.jpg",
    "textparts": "11",
    "lines": "529",
    "version": "N2"
    },
    
"body": [
    {
    "textpart": [{
        "n": "42",
        "subtype": "column",
        "textpartLines": "54",
        "text": [
            "μενοιὀνόματιοὕτως", 
            "καὶἐπὶτῶνστερεῶν", 
            "ἦλθονἐπὶτὰκ_ὰ", 
            "σχήματακαὶἐτίθε", 
            "σανκύβονοὗαἱτρεῖς", 
            "πλευραὶἑκάστηπο", 
            "δόςκαὶγενόμεναιἐ", 
            "πἀλλήλαςποιοῦσιἕν_", 
            "στερεὸνπόδακαὶπρ_", 
            "αιροῦντεςκύβονδύο", 
            "ποδῶνκαὶἄλλοντρι", 
            "ῶνεἶτατεσσάρωνεὕ", 
            "ρισκοναὐτὸμὲντὸ", 
            "στερεὸνπρὸςτὸστερε", 
            "ὸνσύμμετρονἔχει", 
            "γὰρλόγονὃνἀριθμὸς", 
            "πρὸςἀριθμόντὰςδὲ", 
            "πλευρὰςἀσυμμέτρο", 
            "ἄλλουςδὲκύβουςὧν", 
            "τὰστερεὰαἵτεπλευ", 
            "ραὶσύμμετροιἦ_ν", 
            "πρὸςτὸνποδιαῖ_", 
            "κύβονὡςτὸνὀκτώ", 
            "τούτουγὰρπλευρα_ἑ", 
            "κάστηδύοδὶςγὰρδ_ο", 
            "τέσσεραδὶςτέσ_", 
            "κτώκαὶτὸνεἴκ_ἑ", 
            "πτάτρὶςγὰρτρίαἐννέα", 
            "τρὶςἐννέαεἴκοσιἑπτά", 
            "μετέβησανοὖνκαὶἐ", 
            "πὶτούτωνἐπὶτοὺςἀ", 
            "ριθμούςἵναπεριορί", 
            "σωσικαθολικῷτινι", 
            "καὶὥσπερτοὺςἐπιπέ", 
            "δουςτοὺςἰσάκιςἴσο_ἀ", 
            "πείκαζοντῷτετ_α", 
            "γώνῳσχήματικ_ὶ", 
            "ὠνόμαζοντετρα_", 
            "νουςτοὺςδὲἀνισάκις", 
            "ἀνίσουςπρομήκεις", 
            "οὕτωςκἀνθάδετοὺς", 
            "στερεοὺςτοὺςἰσά_ις", 
            "ἴσουςἰσάκιςκύβους", 
            "τοὺςδὲἀνισάκιςἀνί", 
            "σουςἰσάκιςπρομήκ_", 
            "στερεάἐπεὶδὲτῶν", 
            "κύβωνεἰσίντινες", 
            "καὶκατὰτὰστερεὰκαὶ", 
            "κατὰτὰςπλευρὰςσύμ", 
            "μετροιτούτουςδεἴπερ", 
            "ἄραμήκηὠνόμαζον", 
            "τοὺςδὲκατὰμὲντὰ", 
            "στερεὰσυμμέτρους", 
            "κατὰδὲτὰςπλευρὰς"]}, 
        {
        "n": "43",
        "subtype": "column",
        "textpartLines": "30",
        "text": [
            "ἀσυμμέτρο_ςτούτους", 
            "δὲκατὰτὸὅμοι_ντοῖς", 
            "πρ_σθεν_μεις", 
            "στε_άςὡ δἐπὶτῶν", 
            "ἐ_ἀριθμῶν", 
            "_ νἀδύνατοίτ_", 
            "ν_ _οιἰ_άκιςγίνε", 
            "σθα _λἢ_λείων", 
            "ἐλα _ον_ιςἢἐλ_τ", 
            "τω πλεονάκιςἦν", 
            "ἀρι μόςοὕτωςκαὶ", 
            "ἐ _ῶνστερεῶν", 
            "οἱ_ οὖ__ισάκις", 
            "ἄν ἀνισά_ιςσφη", 
            "_ίσ λοῦνται", 
            "οὗτ_ άσαςτὰς", 
            "π_ ἔχουσινἀνί", 
            "σου_οἱ σινἰσάκις", 
            "ἴσο__σάκιςτῶνδὴ", 
            "ά ι__ωνἀνισάκις", 
            "__ἐ _σονάκις", 
            "_λι_θίδεςκαλοῦνται", 
            "ὡςτρ_τ ίαἐννέα", 
            "_ὶςἐνν _δέκαὀκτώ", 
            "_ _γ ρἡτοῦὕ", 
            "_ ε ὰτῶνλοι", 
            "_ῶν δ πλεονάκις", 
            "δο_ _ὡ_δὶςδύο", 
            "τέ_ ατ ςτέσσαρα", 
            "δώδε_α"]}, 
        {
        "n": "44",
        "subtype": "column",
        "textpartLines": "53",
        "text": [
            "ὡςδὲἐντοῖς_ετρα", 
            "γώνοιςὁἑκκ_ίδεκα", 
            "ἀριθμὸςἦνὁ_ὐτ_", 
            "τῆςτεπεριμ_ρ__ὗ", 
            "πλευρὰτέσσερακαὶ", 
            "τοῦἐμβαδοῦκαὶμέ", 
            "σος_δείκνυτοτῆςτε", 
            "ὑπερβολῆςκαὶτῆς", 
            "ἐλλείψεως_ςπρὸς", 
            "ἄλληλατῶντ_πλευ", 
            "ρῶντῶντεπεριμέ", 
            "τρωνοὕτωςκαὶ_ἓξ", 
            "κυβισθεὶςποιε_τὸν", 
            "διακόσιαδέκαἓξἰσά", 
            "ζοντ_τὸνἀρ_ν", 
            "τοῦ _ερεοῦτῷἀρι", 
            "θμῷτῆςπεριμέτρου", 
            "οἱδ ἐντὸςκαὶἐπέ", 
            "κειναἢὑπερβάλλου", 
            "σιἢἐλλείπουσι", 
            "καὶἐπὶτῶνστε ε", 
            "ῶντοίνυνὅσαι_", 
            "γραμμαὶκυβικὸν", 
            "ἀριθμὸνεἰςκυβ", 
            "κὸνσ_ῆμαἀνάγ", 
            "σιτοὺςμὲντ_", 
            "κύβουςμήκη_", 
            "μαζονἐπεὶκ_ὶκα", 
            "τὰμήκηεἰσὶν_ύμμε", 
            "τροιἢἄλλοτιἀνὰλό", 
            "γονὅσαιδὲμὴκυβι", 
            "κὸνἀριθμὸνἀνάγου", 
            "σινεἰςσχῆμακυβι", 
            "κὸνδυνάμειςὠνό", 
            "μαζονἢἄ_οτιἀνὰ", 
            "λόγονδιὰ_ὸἀσυμμέ", 
            "τρουςμὲνεἶναιτοῖς", 
            "μήκεσιτοῖςδὲἀπα_", 
            "τῶνγενομένοις", 
            "συμμέτρους", 
            "ἄριστάγἀνθρώπων", 
            "ὦπαῖδες", 
            "διὰτοῦπροστεθει", 
            "κέναιτὸἄριστα", 
            "γἀνθρώπωνδ_λοῖ", 
            "ὅτισφόδραἀρέσκε", 
            "ταιἔ_ηκενδὲα_τὰ", 
            "καὶἐπῄνεσενδιδά", 
            "σκωνπῶςζητητέ", 
            "ονπρ_τονμὲνοὖν", 
            "ἀπὸτῶνἀσαφε_έ", 
            "ρω__τὰσαφ_τε", 
            "ραδ__εταβαίνειν"]}, 
        {
        "n": "45",
        "subtype": "column",
        "textpartLines": "53",
        "text": [
            "ὡςἀπὸτῶνμεγεθῶν", 
            "μετέβησανἐπὶτοὺς", 
            "ἀριθμού__ε ερον", 
            "δἐπὶτὰ_ ολικώτε", 
            "ρα_ _ονικώ", 
            "τερ νγὰρτῶνκαθἕ", 
            "κασ _ν_ὸπᾶσιτοῖς", 
            "ὁμ_ __φ _όζον", 
            "ὡς __ν_ςμὲνὅ", 
            "ρο__εριέχεταιτὰ", 
            "τε _ά_ωνατὰμή", 
            "κ πὸδὲἑνὸςτὰ", 
            "τε άγων_α_δυνά", 
            "μ_ τ_τονδὲεὐ", 
            "_ρη _ονγίνε", 
            "ται_ _ένἐὰν", 
            "κα _μοειδέ", 
            "σιἡἀ ὴ_φαρμό", 
            "_ _ερκαὶἐνθά", 
            "__ _ἐχρήσαν", 
            "_ἐ_δῳτῇτῶν", 
            "ριθ_ῶνἐπὶτῶν", 
            "πιπέ_νμεγεθῶν", 
            "α__ _ρεῶν", 
            "_ _ἦντοῖς", 
            "_αλ_ _δάσκειν", 
            "καὶ_ _ οἱνεώτε", 
            "_οι _τ_τοῦτοοὕ", 
            "τως_ τάβ_ινεἐπὶ", 
            "τὸκα_ικώτερον", 
            "θ_ώρ_αδιατεῖνον", 
            "_ὶπά_ατὰὅμοια", 
            "_ρη_τον", 
            "_ωσανοὖν", 
            "__ἀ_νοίαςπαλαι", 
            "_ωγῆςἀπ_ιροκα", 
            "ἢφιλοτ_μίαν", 
            "_οτιτοιοῦτοπροσ", 
            "_οντ __Πλά", 
            "_ι_αὶμήνὦ", 
            "_ρατ_ςὅ_εἐρω", 
            "_ερὶἐπ_στήμης", 
            "__υναίμηνἀ", 
            "_ρ νασθαιὥσπερ", 
            "_ ῦμήκουςτε", 
            "_ _ςδυνάμεως", 
            "ὡ__νὶμὲνεἴδει", 
            "πε ιλ_βόντεςτὰ", 
            "ὅμοιατετράγωνα", 
            "μήκηἐκαλέσαμεν", 
            "ἄλλῳδὲδυνάμεις", 
            "οὕτωςοὐδύναμαι", 
            "περὶ_πι_τήμης"]}, 
        {
        "n": "46",
        "subtype": "column",
        "textpartLines": "49",
        "text": [
            "χωρίσαςαὐτ_ντῶν", 
            "ἄλλωνἀποκ_ίν", 
            "σθαιπερὶα_ς", 
            "ἀλλὰτὴνἐπιστήμην", 
            "ὥσπερνυνδὴἐγὼ", 
            "ἔλεγονσμικρόντι", 
            "οἴειεἶναιἐξευρεῖν", 
            "καὶοὐτῶνπάντῃ", 
            "ἄκρωνἐντοῖςπρόσ", 
            "θενἡνίκαπρουκα", 
            "λεῖτοαὐτοὺςεἰς", 
            "κοινολογίανἔφα", 
            "σκενὅτικαὶαὐτὸς", 
            "πειρᾶταιμανθά", 
            "νεινκαὶ_ρὸςμὲν", 
            "τἆλλαπ_ωςἔχει", 
            "ἓνδὲμικρὸνἀπο", 
            "ρεῖπερὶἐπιστήμης", 
            "ὅτιπότἐστίντοῦ _", 
            "τοίνυνἐπανορ_", 
            "ταιὅτιοὔκἐστι_", 
            "μικρὸνεὑρεῖν", 
            "ἀλλὰτῶνἄκρ_", 
            "τιδὲοὔκἐστιντ_", 
            "χόνδῆλονἐκ_οῦ", 
            "δεῖνδιαλαβεῖνπε", 
            "ρίτεοὐσίαςαὐτῆςκαὶ", 
            "εἰδιαφέρειτέχνης", 
            "καὶεἰἐγγίνεταικαὶ", 
            "τοῖςμὴσπουδαί", 
            "οιςκαὶπερὶτῆςὑ_", 
            "βεβλημέν_ςα_", 
            "τῇ_λης_ίἐστιν", 
            "πειρῶμ_ούμε", 
            "νοςτὴνπ_ρὶτῶν", 
            "δυνάμεωνἀπόκρι", 
            "σινὥσπερ_αύτ_ς", 
            "πολλὰςοὔσα_ἑ_ὶ_ἴ", 
            "δειπεριέλαβεςοὕ", 
            "τωςκαὶτὰςπολλὰς", 
            "ἐπιστήμαςἑνὶλ_", 
            "γῳπροσειπεῖν", 
            "αἱγὰρφυσικαὶἔννοι", 
            "αιδέονταιδιαρθρώ", 
            "σεωςπρὸδὲτούτου", 
            "ἐπιβάλλουσιμὲν", 
            "τοῖςπράγμασιτῷ", 
            "ἔχειναὐτῶνἴχνη", 
            "οὐμὴντρανῶςδιὰ"]}, 
        {
        "n": "47",
        "subtype": "column",
        "textpartLines": "48",
        "text": [
            "_τ__ὔτε_Θ_ίτη", 
            "_ο__ν_ _ _εν", 
            "_έγ_πε_ἐ_στή", 
            "_ _τ__οὕ", 
            "_ω_ _οῦσαι ᾴδι", 
            "ονἦ ὡςδι_ελεύ", 
            "ετο_ _ρ _οὐ", 
            "_ὲ__ὴ___παλ", 
            "_αγ_ναιτοῦμέλειν", 
            "ὠ ν_ιςγάρὦφί", 
            "λε αίτητ__ ὰτὸ", 
            "μὴ ενόςἀλλἐγκύ", 
            "_ω_ε _ικ_ίτοι", 
            "μὴ_ _ων", 
            "_Θ _ο_κἀφί", 
            "τα_ _ο_εῖν", 
            "_ ἐ_ή", 
            "_ς _ό__ίν", 
            "___ὡς", 
            "νε _υὴςτ_νκοι", 
            "ῶνἐ_οιῶνκ_", 
            "κ_ἶ τὰς_φ_", 
            "_λυμμέ", 
            "_ςἆ __τιἐπι", 
            "ηδ__ὴναὐτὴν", 
            "χ _ἀ_ήκοας", 
            "ἆροὖν_σθουὅτικαὶ", 
            "α_ὸςτ_αὐτὴντέ", 
            "_ην_ωτῇμη", 
            "ιεύο_αι", 
            "ηςἔ_", 
            "_ _μαιευ_όν", 
            "_ διδασκα ί__ὐ", 
            "_ οιαύτη_ἦν", 
            "_ςμ νγὰρἀπε", 
            "ετ_ _ὶ_χεν", 
            "_ατα_ν_ὲτῷ", 
            "σκειν_τοὺς", 
            "_σκ_ύ_ζεν", 
            "_θάνοντας", 
            "νπε_ὶτῶν", 
            "_ _τωνἀνα", 
            "π_ύ σωναὐτῶν", 
            "τὰς_υ_κὰςἐννοί", 
            "αςκαὶδιαρ_ῶνκαὶ", 
            "τοῦτοἀκό_ θον", 
            "τῷδόγ__ῷτὰς", 
            "λεγο_έν_ς_αθήσεις"]}, 
        {
        "n": "48",
        "subtype": "column",
        "textpartLines": "48",
        "text": [
            "ἀναμνήσειςε _ _", 
            "πᾶσανἀνθρώπου", 
            "ψυχὴντεθεᾶσθαιτὰ", 
            "ὄντακαὶδεῖναὐτῇ", 
            "οὐκἐνθέσεωςμαθη", 
            "μάτωνἀλλὰἀνα", 
            "μνήσεωςπερὶδὲ", 
            "τούτουτοῦδόγματος", 
            "ῥηθήσεταιἐντοῖςεἰς", 
            "τὰΠερὶψυχῆςὑπο", 
            "μνήμασι", 
            "μὴμέντοιμουκατεί", 
            "πῃςπρὸςτοὺςἄλ_υς", 
            "τοῦτοδὲἵναμὴ_ _", 
            "καταφρονήσω_ὡ_", 
            "οὐδενὸςἀξίουοἱδ", 
            "πάνυθαυμάσωσι", 
            "καὶμὴπροσίωσ__", 
            "διότεςἐλέγ_εσ_ι", 
            "οἱδὲἅτεοὐκεἰδότες", 
            "τοῦτομὲνοὐλέγ_σ", 
            "περίμουὅτιδὲἀτ_", 
            "πώτατόςεἰμικαὶ_ι_", 
            "τοὺςἀνθρώπουςἀ", 
            "πορεῖνοἱδὲἀγνο", 
            "οῦντεςὅτιμαιευτι", 
            "κόςεἰμίφασίνμεεἶ", 
            "ναιἀτοπώτατονπα", 
            "ρασκευάζοντατοὺς", 
            "ἄλλουςἀπορεῖνπά", 
            "σχουσιδὲτοῦτοοἱπρ_σ", 
            "ιόντεςδιὰτὸἀναγκά", 
            "ζεσθαιαὐτοὶλέγειν", 
            "περὶτῶνἰδίωνἐν", 
            "νοιῶνοὐδεμίααὐ", 
            "τῶνἔτιαὐτὴκυϊσκο", 
            "μένητεκαὶτίκτουσα", 
            "ἄλλαςμαιεύεται", 
            "αἱμαῖαιμέχριδύναν", 
            "ταικυΐσκεσθαικαὶτί", 
            "κτεινοὐμαιεύονται", 
            "ἀλλὅτανπαραλλάξω", 
            "σιτὸντοιοῦτονχρό", 
            "νον", 
            "ὅτιἄλοχοςοὖσατὴν", 
            "λοχείανεἴληχεν", 
            "κατὰμὲντῆςγαμετῆς", 
            "τὸἄλοχοςἀντὶ_οῦὁ"]}, 
        {
        "n": "49",
        "subtype": "column",
        "textpartLines": "51",
        "text": [
            "μόλ_χοςἣκο_οῦ", 
            "σατ_ῦλέχο_τὸγὰρα", 
            "ἀντ_τοῦὁ_οῦὡ_καὶ", 
            "ἀκό_ο_ἐπὶδὲτῆς", 
            "Ἀρτ_μιδο_τὸ λοχος", 
            "ἀντ_τοῦἐ_μένη", 
            "_χο γὰραἐνθάδε", 
            "σ_ερ_ικὸνὥσπερ", 
            "καὶ_ _ςἀγάμ_υ", 
            "στε _ιςμὲν_ἄρα", 
            "οὐκ_ωκεμαιε εσ", 
            "_ὅτι_ἀ_θρω_ νη", 
            "ςἀ _στέραἢ", 
            "_ _ ηνὧν", 
            "_", 
            "ιςκαὶστεί", 
            "_κεμαιεύ", 
            "_ὴκεκυ", 
            "_δὲτεκεῖν", 
            "_ω_ςοὐδύ", 
            "_ σθαιἐν", 
            "νηνἐνοἷς", 
            "προη", 
            "_αι_ _ατέ", 
            "_ης", 
            "_ ο_ αὶ_δεεἰ", 
            "κόςτεκα ἀναγκαῖον", 
            "τ_κυού ςκαὶμὴ", 
            "γ _ώσκ _αιμᾶλ", 
            "_ __νμαιῶν", 
            "_ _ἳμὴκυοῦ", 
            "σι_ _σιταῖ_ἐγ", 
            "κύ_ιὡςὅσαιὑπο", 
            "β _θαιβουλόμε", 
            "_ _ουσι_αὶπί", 
            "_δι _οῦντα", 
            "_στ_ςτὰςοὖν", 
            "αςκ_μὴδια", 
            "_ουσιαἱμαῖαι", 
            "_νκαὶδιδοῦσαί", 
            "_ _κιααἱμαῖαι", 
            "δουσαιγί", 
            "ν_ ι_γείρειντε", 
            "τὰςὠ_ῖναςκαὶμαλ", 
            "θακ_έρ_ςἐὰνβού", 
            "λωντ_ιποιεῖν", 
            "ὅτανμὲνἐπισπεύ", 
            "δωσιτὰςὠδῖνας", 
            "ἐγείρουσι_ιδοῦσαι", 
            "φαρμάκιατὰσυντα", 
            "χύνοντα _ νδὲ"]}, 
        {
        "n": "50",
        "subtype": "column",
        "textpartLines": "49",
        "text": [
            "παρηγορῶσιτο_ _", 
            "νουςποιοῦσιτ_", 
            "δῖναςβραδίοναςπρότερ", 
            "καὶἐὰννέονὂ_", 
            "ξῃἀμβλίσκει__", 
            "βλίσκουσιν", 
            "τὸνέονἀντὶτο__", 
            "τέλειοντὸτοιο_τ", 
            "οὖνἐὰνδοκῇἐ_", 
            "τρώσκεινπαρα_", 
            "άζουσιτοῦτο", 
            "ὅτικαὶπρομνήστ_", 
            "αίεἰσινδεινόταται", 
            "ὡςπάσσοφοιοὖ_ι", 
            "περὶτοῦγνῶνα_ποί", 
            "ανχρὴποίῳἀνδ_", 
            "συνοῦσανὡςἀρί_", 
            "παῖδαςτ_τειν", 
            "ὡςπροσῆκον _", 
            "μαίαιςἔργοντ__", 
            "μνᾶσθαικατἀλλ_", 
            "λουςκαὶσυναρμόζ", 
            "φησὶνὅτιδεινότα_", 
            "εἰσινσυνορᾶνπ", 
            "ταπὴνδεῖποταπ_", 
            "συνοικοῦσανἀρί", 
            "στουςπαῖδαςτίκτει", 
            "παραδηλοῖὅτιοἱγ_", 
            "μοιπαιδοποιΐαςχ", 
            "ρινοἱκατὰφύσι__αὶ", 
            "τούτωνδὲκρε_ους", 
            "οἱχάριντο_ἀρίσ_υ", 
            "γεννᾶνεἰςγυν_ῖκα", 
            "δέὦφίλεἄλλη_μὲν", 
            "οἴειτοῦτοιούτουἄλ", 
            "ληνδὲσυγκομ_", 
            "τῆςαὐτῆςἀπέφη", 
            "νεντέχνηςτῆςγε", 
            "ωργικῆςτὸεἰδέναι", 
            "τοὺςκαρποὺςσυλλέ", 
            "γεινκαὶἐπίστασθαι", 
            "ποίᾳγῇἁρμόζει", 
            "ποῖασ_έρματακα", 
            "τὰταὐτὰτοίνυνἡαὐ", 
            "τὴἔσταιτέχνηἡ", 
            "σκεψομένηπερὶ_ῶν", 
            "εἰςγυναῖκασπερμά", 
            "τωνποῖἁρμόττει", 
            "καὶπερὶτῆς_ούτων"]}, 
        {
        "n": "51",
        "subtype": "column",
        "textpartLines": "47",
        "text": [
            "μαι_ύσεωςαὕ_ηγὰ_", 
            "ἀναλογε τῇ_ο", 
            "μιδῇοὐ ἔστ_ν_ὲ", 
            "ὅμοιονο _ὰρψ_ ῶς", 
            "ὕληςλό_ ἐπ_ ει", 
            "ἡγ ὴ _δὲ_ἀνὴρ", 
            "τοῦσπέ _ατοςἀλ", 
            "λὰ_κά_ _ςαὐτῶν", 
            "_ψυ_ _ιν_", 
            "τ_ _ο γ_υἐστὶν", 
            "_ _ό_ _οὺς", 
            "κ _υτῆς", 
            "_ μηα", 
            "_ αςἔλε", 
            "_ _α_", 
            "_ α", 
            "ψ _ὰ__", 
            "ε_ _ _", 
            "_ _", 
            "_ _", 
            "ἀ_ νά δὲ", 
            "μὴ _δ_ _ ἶναι", 
            "δ_ _ῶ_ _εἰγὰρ", 
            "προ_ῆνμ_γιστό_", 
            "τεκ ὶκάλλ_τονἔρ", 
            "γον ___ςμ_ί", 
            "αις _ντἀ", 
            "λη_ _ μήαἱ", 
            "γυναῖ_ _ὁτὲμὲν", 
            "εἴδω κτουσιν", 
            "ὅτα _ατίκτω", 
            "σι_ _ αὁ_ὲ", 
            "δ _ῆ_ _νκα", 
            "τὰ _οὐτοῦ__ὖν", 
            "φη __ οὐπρόσε_", 
            "τι___υναιξὶτὸ", 
            "πο_ὲ_ _εἴδωλα", 
            "αὐ__ _εινποτὲ", 
            "δὲἀληθ_νάψεῦδος", 
            "γὰρτοῦτ_ἀλλὰἂνὑ", 
            "περβιβάσῃςἔσται", 
            "σαφέςοὐγὰρπρ_σεσ", 
            "τινταῖςγυναιξὶτὸ", 
            "μὴῥᾴδιονεἶναιδια", 
            "γνῶναιὅτε_ὲνεἴ", 
            "δωλατίκτει_", 
            "δὅτεἀληθιν_εἰγὰρ"]}, 
        {
        "n": "52",
        "subtype": "column",
        "textpartLines": "47",
        "text": [
            "προσῆντίδέεἰπροσ", 
            "ῆντὸμὴῥᾴδιονεἶ", 
            "ναιδιαγινώσκειν", 
            "πότεμὲνεἴδωλα", 
            "τίκτουσινπότεδὲ", 
            "ἀληθινάκάλλιστον", 
            "ἂνἦναὐτῶνἔργον", 
            "εἰδιέκρινοντὸἀλη", 
            "θὲςκαὶμήνῦνδοὔ", 
            "κἐστιδύσκολοςἡτῶν", 
            "τοιούτωνδιάγνω", 
            "σις", 
            "μέγιστονδὲτοῦτἔνι", 
            "τῇἡμετέρᾳτέχνῃ", 
            "βασανίζεινδυνα", 
            "τὸνεἶναιπαντὶτρό", 
            "πῳπότερονεἴδω", 
            "λονκαὶψεῦδοςἀπ_", 
            "τίκτειτοῦνέουἡδι_", 
            "νοιαἢγόνιμόντε", 
            "καὶἀληθές", 
            "ἐδήλωσενὅτιοὐτοῦ", 
            "τοἔλεγενἄνωὅτι", 
            "οὐπρόσεστινταῖςγυ", 
            "ναιξὶντὸὁτὲμὲν", 
            "εἴδωλατίκτεινὁτὲ", 
            "δὲἀληθινάἀλλὰὅτι", 
            "οὕτωςἀκουστέον", 
            "ὡςἐξηγησάμεθα", 
            "κατὰτοῦτοοὖνπ_ε", 
            "σβεύειτὴνἑαυ_οῦ", 
            "μαιευτικὴνμᾶλ", 
            "λοντῆςτῶνγυναι", 
            "κῶνὅτιπαρἐκεί", 
            "ναιςμὲνοὔκἐστι_", 
            "δύσκολονδιαγνῶ", 
            "ναιτὸτεχθένεἰεἴ", 
            "δωλόνἐστινἢἀ", 
            "ληθέςτὰςδὲτῶν", 
            "νέωνδιανοίαςοὐ", 
            "ῥᾴδιονδιαγνῶναι", 
            "πότεραψευδεῖςἔ", 
            "χουσιδόξαςἢἀλη", 
            "θε ςἐπιζητήσει", 
            "ε_ἄντιςεἰδύναται", 
            "εἴ_ωλονεἶναιἢ", 
            "ψ_δοςὃἐννοεῖ"]}]
    }]
}