{

"head": {   
    "tm": "154378",
    "side": "1",
    "noRom": "0",
    "part": "0",
    "graphicName": "P_13891_R.jpg",
    "textparts": "1",
    "lines": "12",
    "version": "N1"
    },

"body": [
    {
    "textpart": [{
        "n": "1",
        "subtype": "column",
        "textpartLines": "12",
        "text": [
            "π απλήσιον γ ρ οἱ το ο", 
            "π σχ υσ ν σπ ρ ἂν εἴ τ ς", 
            "π τήσαιτο", 
            "ν τά", 
            "πλο το", 
            "ματα", 
            "δὲ χ", 
            "πολ", 
            "", 
            "", 
            "ὐσί", 
            ""]}]
    }]
}