{
"textpart": [{
    "n": "1",
    "subtype": "",
    "graphicURL": "",
    "graphicType": "",
    "text": 
    [
    {"ἀ δρεῖονοὐκἔμπλη},{"κτονἀλλὰστάσιμον},{"οἵτεαὖἐμβριθέστε},{"ροινωθροίπωςἀπαν},{"τῶσινπρὸςτὰςμαθή},{"σειςκαὶλήθηςγέμον},{"τες οἱδὲβαρύτεροιοὐ},{"κἔχοντεςτὸὀξὺἀμ},{"βλύτεροίεἰσινἐντῷ},{"μανθάνεινκαὶἐπι},{"λήσμονεςγίνονται},{"κατὰμὲνοὖντοὺςπα},{"λαιούςἐπεὶπολλαὶαἱ},{"ἀρεταὶκαὶκατὰ},{"ἑκάστηνμίαεὐφυΐα},{"ζητηθήσεταιεἰἀν},{"ακολουθοῦσιἀλ ή},{"λαιςαἱεὐφυΐαι ὁ},{"μολογεῖταιτὸμὴ},{"τωςοὐμέντοιἀδύν},{"τοντὸνμίανἔχον α},{"καὶτὰςἄλλαςἔχειν},{"τὰδὲτοὺςΣτωϊκοὺς},{"οὐδὲζητεῖταιτοῦτ},{"μίανγεὑποβάλλο},{"ταςεὐφυΐα},{"τ ῖςἀρεταῖ εἰκ ζ},{"γ ρτὸἡγ ο ν},{"ρῷεὐπ π},{"κότ ν έ},{"χεσθαι ὅ},{"θενοὐδ ἃ},{"ἐρωτᾷἈ},{"οςεἰμία υ},{"ΐαμίαἔ ν ἀ ε},{"τήἀλ νμίαἔσ},{"τινεὐφ ΐ ὡςὁμο},{"λογοῦσιπρὸςοὓςὁλό},{"γοςμίαἄραἔστινἀρε},{"τή ὁδὲοὕτωςλείως},{"τεκαὶἀπταίστωςκαὶ},{"ἀνυσίμωςἔρχεται},{"ἐπὶτὰςμαθήσειςτε},{"καὶζητήσειςμετὰ},{"πολλῆςπρᾳότ τος},{"οἷονἐλαίου μα},{"ψοφητὶῥέοντος οἷ},{"ονδεῖεἶναιἐντα ζη}]{
    "n": "2",
    "subtype": "",
    "graphicURL": "",
    "graphicType": "",
    "text": 
    [
    {"τήσεσι αὶμαθήσεσι},{"ὑπογρ φειὅτιδεῖλεί},{"ωςπροϊέναιτο τἐ},{"στὶν ιαπηδῶν},{"ταἀ στωςμὴ},{"πρ κ ύονταἀ υ},{"σί έ νακαὶ ρο},{"κ τῃδεῖδὲπροσ},{"εῖ αι τὴνπραό},{"τητακ μὴἀγριαί},{"νεινὥ π ρκαὶτὸἔ},{"λαιον εῖἀψοφητί},{"ὥστεθαυμάσαιτὸ},{"τηλικοῦτονὄνταοὕ},{"τωςτα ταδιαπράττε},{"σθαι τὸτηλικοῦτον},{"ἀντὶτ ῦνέονὄντα},{"θαυμα τὸνοὖνεἰκαὶ},{"ἐν ού ῳτῆςἡλικί},{"αςἐμμελῶςζητεῖ},{"εὐαγ εῖς ὑφἓνἀνα},{"γνωστέονἐξακού},{"εται αλὰἀγγέλ},{"ις Θεαίτητοςὦ},{"ρα εςτόγεὄ},{"οῦ ὲνὀνόμα},{"ὸςοὐκ},{"όδωρο},{"αίτη},{"φο},{"τοιο},{"μοιἐ},{"ς εφ},{"ὅ},{"ρὸ τ},{"μ τ λε ερ ό},{"τ θα σ όςὦΣώ},{"ατ ννικὸνλέ},{"ιςτ ν ρα ἐπί},{"τηδε νήσθητοῦ},{"πατρ κα τῆςδια},{"φθορᾶ ῶνχρημά},{"των ῆςὑπὸτῶνἐ},{"ρ ων ναδεί},{"ἐλ υθέ ον},{"ν ῇὡς ε νι}]{
    "n": "3",
    "subtype": "",
    "graphicURL": "",
    "graphicType": "",
    "text": 
    [
    {"κόνἐνγὰ τοῖςμάλι},{"στακαὶτοῦτοσ οπεῖεἰ},{"ἐλευθέριόςἐσ ινὁ},{"νέοςἢοὔὡςτῆςἀνε},{"λευθεριότητοςἱκα},{"νῆςοὔσηςλυμήνα},{"σθα α ὅθ νκἀν},{"τῇ ολ εί ο},{"πῶντοὺ ε φ εῖς},{"κ ήφησ μή},{"ε θῃἀνε θε},{"ριό ςπροσο σα},{"εἰμὲνἄραἡμ τοῦ},{"σώ ατόςτιὁμοίους},{"ησὶνεἶναιἐπαι},{"ν ἢψέγω οὐ},{"νυ τῷἄξ ον},{"ῦνπρ χειν},{"ἔ ὁΘεόδ ος},{"τ ν τητο ῷ},{"Σω τειἐ κ ναι},{"κα ά ετὴνσ μό},{"τ καὶτὸἔξ τῶν},{"ὀμ ωνκατ οῦ},{"το σ αὐ ν},{"εἶ ισ},{"δ},{"},{"τε},{"προ},{"το},{"},{"},{"ιο},{"},{"ρου},{"ν ὴν},{"ῖ},{"τε αὶ ν ο κἄ},{"ιον ὲν κού},{"σα θυ σθ},{"ἀνα κέ ασθ},{"ἐπαινεθ ν δ},{"προθύμ ς},{"ἐπιδεικ ν μ},{"λογήθηα τα}]{
    "n": "4",
    "subtype": "",
    "graphicURL": "",
    "graphicType": "",
    "text": 
    [
    {"ἕκα τον κανὸνεἶναι},{"ἀπ φαίνεσθαιἅπερ},{"κα πειρόςἐστιν},{"τὸ δ Θεόδωρον},{"ἐντοῖςμαθήμασιεἶ},{"ναιἱ ανώτατονἐπεὶ},{"οὖ ὁτοιοῦτοςἐπ},{"νε ὴνψυχήντ ος},{"οὐ διαψευσθεί},{"διὰ οῦτοἄ νσπου},{"δάσ τῷ νἀκού},{"σαν σκ ψασθαιτὸν},{"ἐπαι εθέ αἆράγε},{"τοιο ός τινἢοὔ},{"τῷ ἐ εθέν},{"τι θ ςπαρέ},{"ὑ τασ},{"θη ἀ ὰ},{"μὴ υ μο},{"λογ να τό},{"με αίζ αλέ},{"γειν νδε ἐπ ὶὡ},{"μολ σε ὅ ἐπεὶ},{"πε δευ όδ},{"παιν},{"ψυ},{"ιε υτ},{"ειτ},{"ε},{"ε},{"},{"},{"},{"καὶ ὅρα},{"ωνἔλεγ},{"κνύειὁΣ},{"ὡςαὐτοῦ α},{"ὶοὐ τ έ},{"νον ςτ},{"γ μ οις τ},{"ει αυτ ι},{"ναι μαν ά},{"ουπαρὰΘεοδώ},{"γ ωμετρίαςἄ τ},{"οὐ εἶπεν μανθά},{"δώρουγ}]
}