{

"head": {   
    "tm": "62580",
    "side": "1",
    "noRom": "0",
    "part": "P",
    "graphicName": "P_09782-Pl-P_R_001.jpg",
    "textparts": "1",
    "lines": "194",
    "version": "D4"
    },

"body": [
    {
    "textpart": [{
        "n": "59",
        "subtype": "column",
        "textpartLines": "194",
        "text": [
            "ΠΡΟΝΟΕΙΤΩΝΣΥ[.]ΒΑΛ", 
            "ΛΟΝΤΩΝΠΩΣΔΕ", 
            "ΛΕΓΕΙΟΤΙΟΥΤΕΨΕΥΔΟΣ", 
            "ΑΝΣΥΓΧΩΡΗΣΕΙ[..]", 
            "ΚΑΙΟΥΚΑΛΗΘΕ[.]ΟΥΚΑ[.]", 
            "ΑΦΑΝΙΣΕΙΕΝΧΡΩΜΕ", 
            "ΝΟΣΤΟΥΤΟΙΣΕΝΤΑ[..]ΖΗ", 
            "ΤΗΣΕΣΙΝΕΤΙΔΕΚ[..]Ε[.]", 
            "ΤΗΟΛΕΙΤΕΙΑΕΔΟ[.]Η", 
            "ΟΤΙΤΩΨΕΥΔΕΙΧΡΩΝ", 
            "ΤΑΙΟΙΑΡΧΟΝΤΕΣΕΝΦΑΡ", 
            "ΜΑΚΟΥΕΙΔΕΙΛΕΓΩΤΟΙ", 
            "ΝΥΝΟΤΙ[.]ΝΤΑΙΣΖΗΤΗ", 
            "ΣΕΣΙΠΥΝΘΑΝΕΤΑΙΚΑΙ", 
            "ΟΥΚΑΠΟΦΑΙΝΕΤΑΙΩ[.]", 
            "ΤΕΟΥΤΕΨΕΥΔΟΣΟΥ[..]", 
            "ΛΗΘΕΣΤΙΘΗΣΙΤΟΙΣ", 
            "ΜΕΝΤΟΙΕΜΠΕΙΡΟΙΣ[...]", 
            "ΜΕΘΟΔΟΥΛΕΛΗΘΟΤ[..]", 
            "ΔΕΙΚΝΥΕΙΤΟΕΑΥΤΩ[.]", 
            "ΡΕΣΚΟΝΤΟ[.]ΕΨΕΥΔ[.]", 
            "ΣΘΑΙΑΠΛΩΣΜΕΝΑ[..]", 
            "ΔΟΚΙΜΑΖΕΙΟ[.]Ε[.....]", 
            "ΟΤΙΕΣΤΙΝΠΟ[......]", 
            "ΚΑΙΟΝΔΙΑΤ[........]", 
            "ΠΕΝΑΛΗΘΕΣΚ[.....]", 
            "ΗΠΑΡΕΛΘΕΙΝ[.....]", 
            "ΤΟΙΟΥΤΟΝΕΣΤ[.....]", 
            "ΧΡΗΣΙΜΟΝΑ[.]ΛΑΦΑ", 
            "ΝΙΣΑΙΔΙΑΤΟΥΤΟΥΔΗ", 
            "ΛΩΝΤΗΝΟΥΚΑΤΑΚΑΙ", 
            "ΡΟΝΟΥΔΕΕΝΔΕΟΝΤΙ", 
            "ΤΟΥΑΛΗΘΟΥΣΑΠΩΛΕΙ", 
            "ΑΝΔΟΚΕΙΟΥΝΜΟΙΟΕ", 
            "ΠΙΣΤΑΜΕΝΟΣΤΙΑΙΣΘΑ", 
            "ΝΕΣΘΑΙΤΟΥΤΟΟΕΠΙΣΤΑ", 
            "ΤΑΙΚΑ[.]ΩΣΓΕΝΥΝΦΑΙ", 
            "ΝΕΤΑΙΟΥΚΑΛΛΟΤΙΕΣΤΙΝ", 
            "ΕΠΙΣΤΗΜΗΗΑΙΣΘΗ", 
            "ΣΙΣΟΕΠΙΣΤΑΜΕΝΟΣΤΙ", 
            "ΑΙΣΘΑΝΕΤΑΙΤΟΥΤΟΥ", 
            "ΟΕΠΙΣΤΑΤΑΙΕ[.]ΔΕΤΟ", 
            "ΑΙΣΘΑΝΕΣΘΑΙΕΠ[....]", 
            "ΣΘΑΙΗΝΓΙΝΕ[.]ΑΙΗ", 
            "ΕΠΙΣΤΗΜΗΑΙΣΘΗΣΙ[.]", 
            "ΑΙΣΘΗΣΙΝΝΥΝΟΥΤΟ", 
            "ΑΙΣΘΗΤΗΡΙΟΝ[.]ΚΟΥ", 
            "ΣΤΕΟΝΑΛΛΑΑΝΤΙΛΗΜ", 
            "ΨΙΝΗΝΤΙΝΟΥΝΠΩΣ", 
            "ΕΑΙΤΗΤΟΣΑΝ[.]ΕΠΕ", 
            "ΡΩΤΗΘΕΙΣΠΕΡΙΕΠΙΣΤΗ", 
            "ΜΗΣΤΙΕΣΤΙΝΚΑΙΕ[.]", 
            "ΠΩΝΓΕΩΜ[...]Ι[..]", 
            "ΚΑ[.]ΑΛΛΑΣΚΑ[.]ΑΡΙΘΜΗ", 
            "ΣΑΜΕΝΟΣΝΥΝΕΠΙ[..]Ν", 
            "ΑΙΣΘΗΣΙΝΚΑ[......]ΕΙ", 
            "ΚΑΙΤΑΥΤΑΓ[.]Ω[.....]Σ", 
            "ΩΝΤΗ[.]ΤΕΣ[.]Ν[....]Σ", 
            "ΕΛΕ[.]Χ[..]ΣΗΣ[.......]Η", 
            "ΣΕΙΣ[.][.]Τ[..]Ν[....]", 
            "ΜΕΝ[.]ΝΑΣ[.]ΝΟ[......]", 
            "ΑΠ[...]Ε[..........]", 
            "Ν[...............]", 
            "[.][.]ΤΟ[.......]Α[...]Υ", 
            "[...........]ΠΛΟ[..]", 
            "[........][.]ΝΑΙΣΕ[.]", 
            "[.........]ΚΑΙΜΗ[.]Σ", 
            "[.....][....]ΤΗΜΗΑΛ", 
            "[.][........]ΓΕΤΟΔΕΤΟΥ", 
            "[.........]ΟΥΜΕΤ[.]", 
            "[..........]ΑΓΑΡΑ", 
            "[...][.....]ΓΟΡΕΙΟΣ", 
            "[.........]ΕΝΟΥΕ", 
            "[........][.]ΠΙΣΤΗ", 
            "[.][........]ΣΑΙΣΘΗ", 
            "[...][......]ΑΚΕΙ", 
            "[.....]ΡΙΤ[..]ΚΕΙΝΟΥ", 
            "[.......]Μ[.]ΤΑΟΕ", 
            "[.......]ΣΥΜΒΑΛΩΝ", 
            "[......]ΩΤΩΕΚΕΙ", 
            "[......]ΩΔ[.]ΛΟΙΔΕ", 
            "[.....]ΕΙΔΑ[.]ΠΥΘΟ", 
            "[....]ΥΩΚΡΑΤΟΥΣ", 
            "[....]ΕΤΥΧΕΝΤΩΕ", 
            "[...]ΛΗΘΕ[..]ΣΣΥΓ", 
            "[....]ΜΑΤΙΛ[.]ΓΗΟ", 
            "[.....]ΗΤ[..]ΟΤΙΕΝΤΕ", 
            "[.....]Ε[.]ΠΟΛΛΑΚΙΣ", 
            "[......]ΑΥΜΑΣΤΟΝΕΙ", 
            "[......]ΜΗΝΕΘΕΤΟ", 
            "[......][.][.]ΟΤΕΚΑΙ", 
            "[........]Α[.][.]ΝΠΑ", 
            "[......]ΥΙΔ[.][.]ΟΥΑΙΣΘΗ", 
            "[.....]ΙΣΤΗΜΗΝΕΙ", 
            "[...]ΕΥΓ[.]ΚΑΙΓΕΝ", 
            "[][....]ΣΩΠΑ[.]ΧΡΗΓΑΡ", 
            "[][...]Ω[.]ΠΟΦΑ[.]ΝΟΜΕ", 
            "[][...]ΛΕΓΕΙΝΕΠΕΙΟ", 
            "ΕΑΙΤΗΤΟΣΕΠΕΡΩΤΗ", 
            "ΘΕΙΣΠΕΡΙΕΠΙΣΤΗΜΗΣ", 
            "ΤΙΕΣΤΙΝΕΙΠΕΝΚΑΙ", 
            "ΩΣΓΕΝΥΝΙΦΑΙΝΕΤΑΙ", 
            "ΑΠΟΔΕΧΕΤΑΙΩΚΡΑ", 
            "ΤΗΣΟΤΙΟΥΚΟΚΝΕΙΛΕ", 
            "ΓΕ[.]ΝΟΦΑΙΝΕΤΑΙΑΥ", 
            "ΤΩΚΑΙΝΟΜΙΖΕΙΕΙ", 
            "ΝΑΙΤΗΝΕΠΙΣΤΗΜΗΝ", 
            "ΟΥΓΑΡΕΚΕΙΝΟΦΗΣΙΝ", 
            "ΤΟΥΡΡΩΝΕΙΟΝΟΤΙ", 
            "ΟΥΔΕΝΚΑΘΟΡΙΣΤΙΚΩΣ", 
            "ΑΝΤΙΣΔΟΓΜΑΤΙΖΟΙ", 
            "ΑΛΛΑΦΗΣΙΝΦΑΙΝΕΣ", 
            "ΘΑΙΑΥΤΩΚΑΤΑΓΑΡΤΟΝ", 
            "ΑΝΔΡΑΟΥΤΕΟΛΟΓΟΣ", 
            "ΚΡΙΤΗΡΙΟΝΟΥΤΕΑΛΗ", 
            "ΘΗΣΦΑΝΤΑΣΙΑΟΥΤΕ", 
            "ΠΙΘΑΝΗΟΥΤΕΚΑΤΑ", 
            "ΛΗΠΤΙΚΗΟΥΤΕΑΛΛΟ", 
            "ΤΙΤΟΙΟΥΤΟΝΑΛΛΟΤΙ", 
            "ΝΥΝΑΥΤΩΦΑΙΝΕ[.]ΑΙ", 
            "ΕΙΔΕΤΟΙΟΥΤΟΝΕΣΤΙΝ", 
            "ΗΟΥΚΕΣΤΙΝΟΥΚΑΠΟ", 
            "ΦΑΙΝΕΤΑΙΔΙΑΤΟΟΙΕ", 
            "ΣΘΑΙΙΣΟΚΡΑΤΕΙΣΕΙ", 
            "ΝΑΙΤΟΥΣΕΙΣΤΑΕΝΑΝ", 
            "ΤΙΑΛΟΓΟΥΣΚΑΙΕΞΟΜΑ", 
            "ΛΙΖΕΙΝΤΑΣΦΑΝΤΑΣΙ", 
            "ΑΣΚΑΙΜΗΔΕΜΙΑΝΕΝ", 
            "ΑΥΤΑΙΣΑΠΟΛΕΙΠΕΙΝ", 
            "ΔΙΑΦΟΡΑΝΚΑΤΑΤΟΑ", 
            "ΛΗΘΕΣΗΨΕΥΔΟΣΠΙ", 
            "ΘΑΝΟΝΗΑΠΙΘΑΝΟΝ", 
            "ΕΝΑΡΓΕΣΗΑΜΥΔΡΟΝ", 
            "ΚΑΤΑΛΗΠΤΟΝΗΑΚΑ", 
            "ΤΑΛΗΠΤΟΝΑΛΛΑΠΑ", 
            "ΣΑΣΕΙΝΑΙΟΜΟΙΑΣΟΥ", 
            "ΔΕΤΟΥΤΟΔΟΓΜΑΤΙ", 
            "ΖΟΝΤΟΣΩΣΕΠΕΤΑΙ", 
            "ΤΟΔΙΕΞΑΓΕΙΝΚΑΤΑ", 
            "ΤΗΝΑΕΙΠΡΟΣΠΙΠΤΟΥ", 
            "ΣΑΝΦΑΝΤΑΣΙΑΝΟΥ", 
            "ΧΩΣΑΛΗΘΗΑΛΛΟΤΙ", 
            "ΝΥΝΑΥΤΩΦΑΙΝΕ", 
            "ΤΑΙΚΙΝΔΥΝΕΥΕΙΣ", 
            "ΜΕΝΤΟΙΛΟΓΟΝΟΥΦΑΥ", 
            "ΛΟΝΕΙΡΗΚΕΝΑΙΠΕΡΙ", 
            "ΕΠΙΣΤΗΜΗΣΑΛΛΟΝ", 
            "ΕΛΕΓΕΝΚΑΙΡΩΤΑΓΟ", 
            "ΡΑΣΤΡΟΠΟΝΔΕΤΙΝΑ", 
            "ΑΛΛΟΝΕΙΡΗΚΕΝΤΑΑΥ", 
            "ΤΑΤΑΥΤΑΦΗΣΙΝΓΑ[.]", 
            "ΠΟΥΠΑΝΤΩΝΧΡΗ[..]", 
            "ΤΩΝΜΕΤΡΟΝΑΝΘΡ[.]", 
            "ΠΟΝΕΙ[.]ΑΙΤΩΝΜ[..]", 
            "ΟΝΤΩΝΩΣΕΣΤ[..]", 
            "ΤΩΝΔΕΜΗΟΝΤΩΝ", 
            "[]ΩΣΟΥΚΕΣΤΙ[.]ΚΑ[.]Α[.]", 
            "ΤΟΣΗΠΙΣΤΑ[..]ΟΤΙΔΙ[.]", 
            "ΦΕΡΕΙΗ[.]ΩΤΑΓΟΡΟ[.]", 
            "ΔΟΞΑΤΗΣ[.]ΑΙΤΗ[...]", 
            "ΠΕΡΙΕΠ[.]ΣΤ[.]ΜΗ[.]", 
            "ΔΙΑΤΟΥΤΟ[...]Ε[...]", 
            "ΔΥΝΕΥΕ[.........]", 
            "ΦΑΥΛ[.]Ν[.........]", 
            "ΤΡΟ[....]ΕΤ[.......]Ν", 
            "Ε[.......]ΑΥ[...]ΑΥΤΑ", 
            "Β[.][.........]ΟΜΟΥ", 
            "[............]ΩΝ", 
            "[............]ΤΑ", 
            "[.............]Η", 
            "[............]ΕΝ", 
            "[............][.]Σ[..]", 
            "Δ[....][.][......]ΣΙ[..]", 
            "ΑΛΗΘΗ[......]ΝΟΝ", 
            "ΔΙΟΥΚΡ[.......]ΗΣ[.]Ν", 
            "ΓΑΡΕΙΝ[........]Ν", 
            "ΓΝΩΜ[......]ΗΣΔΕ", 
            "ΤΟΜΕ[.....]Φ[.]ΣΙΣ", 
            "ΑΝΤΙΤΗ[....]ΘΗΣΕΩΣ", 
            "ΤΑΣΣΟΜ[....]ΤΟΔΕΝΟ", 
            "ΜΟΣΑΝΤ[....]ΔΟΞΗΣ", 
            "ΠΑΝΤ[.......]ΤΑΥΤ[.]", 
            "ΠΡΟ[.......]ΕΔ[.]Α", 
            "Τ[.]ΡΕΙ[.....]ΛΑΜΒΑ", 
            "ΝΕΣΘ[..........]ΝΟ", 
            "ΜΕΝΟΝ[......]ΚΡΙ", 
            "ΝΟΝΤ[......]ΣΤΙΤΟ", 
            "ΕΝΤΗΝ[.......]ΣΕ", 
            "ΤΕΡΟΝΚΑΙΝ[..]ΥΜΕ", 
            "ΝΟΝΚΑΙΛ[.....]ΝΟΝ", 
            "ΚΑΙΥΦΕΣΤΟ[.]Ω[.]ΔΕΞΙ", 
            "ΟΣΑΡΙΣΤΕΡΟΥΔΕΞ[.]ΟΣ", 
            "ΩΣΤΟΟΜΟΙΟΝΟΜΟΙΩ", 
            "ΟΜΟΙΟΝΩΣΤ[.]ΜΕΓΑ"]}]
    }]
}