<?xml version="1.0" encoding="UTF-8"?><map xmlns="http://www.w3.org/2005/xpath-functions"><map key="head"><string key="tm">62580</string><string key="side">1</string><string key="noRom">0</string><string key="part">R</string><string key="graphicURL">http://berlpap.smb.museum/Original/P_09782-Pl-R_R_001.jpg</string><string key="graphicName">62580_67-71__PBerol9782_Pl_R_R.jpg</string><string key="textparts">5</string><string key="lines">215</string><string key="version">N2</string></map><array key="body"><map><array key="textpart"><map><string key="n">67</string><string key="subtype">N/A</string><string key="textpartLines">43</string><array key="text"><string>ταιἕκ _ _α</string><string>στ δὲ</string><string>ωκ _</string><string>_</string><string>_</string><string>_</string><string>_</string><string/><string>_ατ_</string><string>ἐστιν_</string><string>_ὡςἐπιστ_</string><string>_ειὅτιἔσ</string><string>καθαὑ</string><string>νασκευ</string><string>_ταγό</string><string>_ιτων</string><string>πάντα</string><string>_κεν</string><string>οιο</string><string>εἰἡ</string><string>_ ἐ_ υγχά</string><string>_το_ ὃςαὐτὴν</string><string>ἐ_ιτυγ</string><string>_α</string><string>_γίνεταιἐ</string><string>_μητ_τοδὲ</string><string>_ ρασμα</string><string>_ λό_υ</string><string>_δ__ό_α</string><string>_ὶμάλ_ὐ</string><string>όγονὡ ἄ</string><string>_αὐτὸκαθαὑ</string><string>_ἐστινοὐ</string><string>οσείποις</string><string>δὁποιον</string><string>_κεὐκατα</string><string>_ νφησιν</string><string>τὸ ντὸνπερὶ</string><string>το_ __ὰς_ὐσίας</string><string>κα_ _ ξον</string><string>_ _ γὰρτα_</string><string>τῇ ςποιη</string><string>_ __λ_</string></array></map><map><string key="n">68</string><string key="subtype">N/A</string><string key="textpartLines">49</string><array key="text"><string>στοιοὐδὲνοὖνἔστιν</string><string>αὐτὸκαθαὑτότοῦτἐσ</string><string>τίνοὐδὲνκαθαὑτὸ</string><string>ἔχειτὴνὑπόστασιν</string><string>τοῦτἐστίνοὐδὲνκα</string><string>τὰἰδίανἀλλὰπάντα</string><string>πρόςτιτὴνμὲν_ὖν</string><string>οὐσίανδηλοῖεἰπ ν</string><string>οὐδἂντίπροσείπ_ις</string><string>τὸγὰρτίἐμφαίνειοὐ</string><string>σίαντὸδὲποσὸνδιὰ</string><string>τοῦεἰρηκέναιἓνμὲν</string><string>αὐτὸκαθαὑτότὸδὲ</string><string>ποιὸνδιὰτοῦὁποιον</string><string>οῦντιἀλλἐὰνὡ_</string><string>μέγαπροσαγορεύῃς</string><string>καὶσμικρὸνφανεῖ</string><string>ταικαὶἐὰνβαρύκοῦ</string><string>φοντὸμέγακαὶτὸ</string><string>σμικρὸνκαὶβαρὺ</string><string>καὶκοῦφοντῶνπρός</string><string>τίἐστινκατὰγὰρ_</string><string>πρὸςἕτερονσχέ_</string><string>θεωρεῖταιοὐδὲνοὖν</string><string>καθἑαυτόἐστινμέ</string><string>γαἦνγὰρἂνἀεὶμέγα</string><string>νῦνδὲτὸαὐτὸμι</string><string>κρὸνφαίνεταισυμ</string><string>βληθὲνἑαυτοῦμεί</string><string>ζονιὁμοίωςδὲ_ὶ</string><string>ἐπὶσμικροῦκαὶβα</string><string>ρέοςκαὶκούφουὅτι</string><string>νῦνμὲντοῖανῦνδὲ</string><string>τοῖαφαίνεταικατὰ</string><string>τὰςπρὸςἄλλοκαὶἄλ</string><string>λοσχέσεις</string><string>ξύνπαντάτεοὕτως</string><string>ὡςμηδενὸςὄντοςἑνὸς</string><string>μήτετινὸςμήτεὁ</string><string>ποιουοῦνὥσπερ</string><string>οὐδὲνἦνμέγαεὑρί</string><string>σκετογὰρτὸαὐτὸμι</string><string>κρόνοὕτωςκαὶτἆλ</string><string>λαπάνταἐπιδέχε</string><string>ταιτὰςἐναντίαςκα</string><string>τηγορίαςδιὰτὸμη</string><string>δὲνεἶναιἕντοῦτἐσ</string><string>τὶνμὴἔχεινὡρισ</string><string>μένηνποσότητα</string></array></map><map><string key="n">69</string><string key="subtype">N/A</string><string key="textpartLines">24</string><array key="text"><string>ν_</string><string>συμβάλῃ_</string><string>οῦτοαπετ</string><string>ἀμφοῖν_</string><string>καὶαὐτ_</string><string>νονπαντα</string><string>ταιδιο</string><string>αῦταὄν</string><string>ρεύομ_</string><string>στι__</string><string>__</string><string>_α_</string><string>μ ιοῦται_</string><string>__ίως_</string><string>σθ_ιγὰρ_</string><string>τὸναὐτ_</string><string>κηνλα_</string><string>μοίωςδὲ_</string><string>ώσεωςτο_</string><string>αὐτὸνγί_</string><string>τοναἀντ_</string><string>γὰρταῦτα λ</string><string>αὔξησις _ί</string><string>ἰδίωςπ</string></array></map><map><string key="n">70</string><string key="subtype">N/A</string><string key="textpartLines">49</string><array key="text"><string>_χωρηθέντοςἑνὸς</string><string>_ωνκαὶτὰλοιπὰ</string><string>_όσθαικαὶἀναιρε</string><string>_τοςκαὶτὰλοιπὰ</string><string>ῃρῆσθαιτὸνδὲ</string><string>ὶτοῦαὐξομένου</string><string>_ονἐκίνησεν</string><string>ὲνπρῶτοςΠυθα</string><string>_αςἐκίνησεν</string><string>καὶΠλάτωνὡςἐν</string><string>_ςεἰςτὸΣυμπόσιον</string><string>_μνήσαμενἐπι</string><string>ροῦσιδὲεἰςαὐτὸ</string><string>οἱἐξἈκαδημείας</string><string>_ ρτυρόμενοιμὲν</string><string>ὅ_ιἀρέσκονταιτῷ</string><string>εἶναιαὐξήσειςδιὰδὲ</string><string>τὸτοὺςΣτωϊκοὺςκα</string><string>τασκευάζειντοῦτο</string><string>οὐδεόμενονἀποδεί</string><string>ξεω διδάσκοντες</string><string>ὅτιἐάντιςτὰἐναργῆ</string><string>θέλῃἀποδεικνύ</string><string>ναιἕτεροςεἰςτὸἐνα_</string><string>τίονπιθανωτέρων</string><string>εὐπορήσειλόγων</string><string>καὶπερὶτούτουπάν</string><string>τεςἐξαίσιοιοἱσοφοὶ</string><string>πλὴνΠαρμενίδου</string><string>συμφέρεσθονΠρωτα</string><string>γόραςτεκαὶἩράκλει</string><string>τοςκαὶἘμπεδοκλῆς</string><string>περὶτοῦφέρεσθαι</string><string>_άνταπάντεςσοφοὶ</string><string>υμφωνοῦσινὑπε</string><string>ξῃρημένουΠαρμε</string><string>_ίδουοὗτοςγὰρἀπο</string><string>_λέψαςεἰςτὴντοῦεἴ</string><string>δουςφύσινπαρελ</string><string>θὼνδὲτὴνὕλην</string><string>φησίνοἶονἀκίνη</string><string>τόντεθέλειτῷπαν</string><string>τὶὄνομαεἶναιπε</string><string>ρὶμὲνοὖντῶνἄλλων</string><string>φυσικῶνῥᾴδιον</string><string>λαβεῖνὅτιφασὶνφέ</string><string>ρε_θαιπάνταἀλλὰ</string><string>κ_Ἐμπεδοκλῆςἀ</string><string>_ροὰςἀπολείπει</string></array></map><map><string key="n">71</string><string key="subtype">N/A</string><string key="textpartLines">50</string><array key="text"><string>καί_</string><string>χν ύο_</string><string>κέρ_</string><string>μελέων</string><string>τοῦ_όγὅτ</string><string>θν_ _ο_</string><string>__ _</string><string>_ _ῆς</string><string>ω _τέρα_</string><string>δ_ _μὲνἘπί</string><string>τρ_γῳδίαςδ_</string><string>Ἐπίχαρμοςὁ</string><string>σαςτοῖςΠυθα</string><string>ἄλλατ τ_ναε_</string><string>κ_νδ _α_</string><string>_ῦ_ξο_</string><string>_ ἐφοδ</string><string>_ _ρα</string><string>ἀλλ__</string><string>ταιπρόσ_</string><string>_έςεἰοὖ_</string><string>γ_ ται_</string><string>_ _ων_</string><string>οὐσίαιἄλλ</string><string>γίνο_αι</string><string>εχῆῥύσιν_ _</string><string>δησεναὐτὸἐ_ὶτοῦἀ</string><string>παιτου_ένουσ_μβ_</string><string>λὰςκαὶ _νουμένου</string><string>τ_ῦαὐτοῦεἶναιδιὰτὸ</string><string>τὰμὲνπροσγεγενῆ</string><string>σθαιτὰδὲἀπεληλυ</string><string>θέναιἐπεὶδὲὁἀπαι</string><string>τῶνἐ_ _ησεναὐ</string><string>τὸνκα_ἐ_εκαλε_</string><string>πάλινκ κ_</string><string>σκοντο_ _μ_ _</string><string>ναιτὸν_ πτ_κό</string><string>ταἕτερο _ὸ_ἐγ</string><string>καλού_ _ον_μη</string><string>ρονδὲτρ γῳδίαςεἶ</string><string>πενποι_ήνἐπεὶ</string><string>τὸπαλα _ἡντιν</string><string>οῦνποί_ _νπεριέ</string><string>χουσαν_ ωϊκὰςπρά</string><string>ξει__ μαζοντρα</string><string>γῳδ_ τίςοὖνἂν</string><string>ἔτιπρός _οσοῦτο</string><string>στρατόπ_ νκαὶ_</string><string/></array></map></array></map></array></map>