{

"head": {   
    "tm": "62580",
    "side": "1",
    "noRom": "0",
    "part": "B",
    "graphicName": "P_09782-Pl-B_R_001.jpg",
    "textparts": "1",
    "lines": "179",
    "version": "D4"
    },

"body": [
    {
    "textpart": [{
        "n": "7",
        "subtype": "column",
        "textpartLines": "179",
        "text": [
            "ΠΛΗΣΙΟΝΕΑΝΟΥΝΑΠΟ", 
            "ΛΕΙΠΗΤΕΥΜΕΙΣΑΝΟ", 
            "ΜΟΙΑΝΑΡΑΓΕΟΥΧΟΡΑ", 
            "ΤΕΟΤΙΤΟΥΤΟΤΟΠΛΕΙ", 
            "ΟΝΑΝΑΓΚΑΣΕΙΠΟΤΕ", 
            "ΜΗΟΜΟΙΩΣΣΤΟΧΑ", 
            "ΖΕΣΘΑΙΤΟΥΤΕΕΑΥΤΩΝ", 
            "ΛΥΣΙΤΕΛΟΥΣΚΑΙΤΟΥ", 
            "ΤΩΝΠΛΗΣΙΟΝΕΞΑΡ", 
            "ΚΕΙΔΕΚΑΙΕΠΙΤΕΧΝΗΣ", 
            "ΚΑΙΕΠΙΑΡΕΤΗΣΠΑΡΑ", 
            "ΒΑΘΕΙΣΚΑΝΕΙΣΑΡΙΘΜΟΣ", 
            "ΕΚΑΤΕΡΟΝΑΥΤΩΝΑ", 
            "ΦΑΝΙΣΑΙΟΘΕΝΟΥΚΑ", 
            "ΠΟΤΗΣΟΙΚΕΙΩΣΕΩΣ", 
            "ΕΙΣΑΓΕΙΟΛΑΤΩΝΤΗΝΔΙ", 
            "ΚΑΙΟΣΥΝΗΝΑΛΛΑΑ", 
            "ΠΟΤΗΣΠΡ[.]ΣΤΟΝΘΕ", 
            "ΟΝΟΜΟΙΩ[...]ΣΩΣΔΕΙ", 
            "ΞΟΜΕΝΤΗ[...]ΟΙΚΕΙ", 
            "ΩΣΙΝΤΑΥ[...]ΠΟΛΥ", 
            "ΘΡΥΛΗΤΟΝΟΥΜΟ[..]Ν", 
            "ΟΩΚΡΑΤΗΣΕΙΣ[..]ΕΙ", 
            "ΑΛΛΑΚΑΙΟΙΠΑΡΑΤΩ", 
            "ΛΑΤΩΝΙΣΟΦΙΣΤ[..]", 
            "ΑΥΤΗΣΔΕΔΗΤΗΣΟΙ", 
            "ΚΕΙΩΣΕΩΣΗΜΕΝ", 
            "Ε[.]ΤΙΝΚΗΔΕΜΟΝΙΚΗ", 
            "[.......]Υ[.......]", 
            "[.]Ρ[..]ΤΟΥΣΠΛ[.......]", 
            "Τ[..]ΩΣΑΝΤΙΕΙ[.]ΣΟΙ", 
            "[...............]ΑΙ", 
            "ΡΟ[.]ΜΕΘΑΕΑΥΤΟΙΣΤΑ", 
            "ΓΑ[.]ΑΟΥΚΑΥΤ[.....]", 
            "Κ[......]ΚΗΔΟΜΕΝΟΙ", 
            "Α[.]ΛΑΒΟΥΛΟΜΕΝΟΙ", 
            "ΑΥΤΑΓΕΝΕΣΘΑΙΗΜΙΝ", 
            "ΔΗΛΟΙΟΤΙΗΠΡΟΣΕΑΥ", 
            "ΤΟΝΚΑΙΤΟΥΣΟΜΟΕΙΔΕΙΣ", 
            "ΟΥΚΕΣΤΙΝΑΙΡΕΤΙΚΗ", 
            "ΟΥΔΕΙΣΓΑΡΑΙΡΕΙΤΑΙΕ", 
            "ΑΥΤΟΝΑΛΛΑΕΑΥΤΟΝ", 
            "ΜΕΝΕΙΝΑΙΤΑΓΑΘΟΝ", 
            "ΔΕΕΑΥΤΩΕΙΝΑΙΚΗΔΕ", 
            "ΤΑΙΔΕΕΑΥΤΟΥΚΑΙΤΩΝ", 
            "ΠΛΗΣΙΟΝΔΙΑΤΟΥΤΟΕ", 
            "ΦΗΕΙΜΕΝΤΩΝΕΝΥ", 
            "ΡΗΝΗΜΑΛΛΟΝΕΚΗ", 
            "ΔΟΜΗΝΔΗΛΩΝΟΤΙΗ", 
            "ΤΟΙΑΥΤΗΟΙΚΕΙΩΣΙΣ", 
            "ΕΣΤΙΝΚΗΔΕΜΟΝΙΚΗ", 
            "ΚΑΙΜΑΛΛΟΝΕΠΙΘΥ", 
            "ΜΩΕΙΔΕΝΑΙΤΙΝΕΣΗ", 
            "ΜΙΝΤΩΝΝΕΩΝΕΠΙ", 
            "ΔΟΞΟΙΓΙΝΕΣΘΑΙΕΠΙ", 
            "ΕΙΚΕΙΣΚΑΙΠΕΡΙΤΩΝ", 
            "ΕΝΘΑΔΕΝΕΩΝΕΙΠΕΡ", 
            "ΠΕΡΙΤΩΝΕ[..]ΥΡΗΝΗ", 
            "ΜΑΛΛΟΝΕΠΙ[.]ΥΜΩΕΙ", 
            "ΔΕΝΑΙΤ[.]ΝΕΣΥΠΟΦΑΙ", 
            "ΝΟΥΣΙΕΛΠΙΔΑΣΤΟΥΓΕ", 
            "ΝΕΣΘΑΙΜΕΤΡΙΟΙΤΑΥ", 
            "ΤΑΔΗΑΥ[...]ΤΕΣΚΟ", 
            "ΠΩΚΑΘΟΣ[..]ΔΥΝΑ", 
            "ΜΑΙΚΑΙΤΟΥΣΑ[..]ΟΥΣ", 
            "ΕΡΩΤΩΟΙ[........]ΥΣ", 
            "ΝΕΟΥΣΕΘΕΛΟΝΤ[..]", 
            "ΣΥΓΓΙΓΝΕΣΘΑΙΕΝ[..]ΙΣ", 
            "ΕΡΩΤΙΚΟΙΣΛΕΓΕΤΑΙ", 
            "ΟΤΙΤΟΥΣΠΟΥΔΑΙΟΥΕ", 
            "ΣΤΙΝΤΟΓ[.]ΩΝΑΙΤΟΝ", 
            "ΑΞΙΕΡ[..]ΤΟΝΖΗΤΕΙ", 
            "ΤΑΙΟΥΝΠΩΣΟΕΑΙ", 
            "ΤΗΤΟΣΕΛ[...]Ν[....]Ν", 
            "ΩΝΕ[.]ΦΥΗ[.......]", 
            "ΤΕΟ[..]ΟΙΝΥΝΟ[..]ΟΥ", 
            "ΔΕΟΥΤΟΣΑΥΤΟΝΕΛΑ", 
            "ΘΕΝΟΥΠΑΝΤΑΣΓΑΡ", 
            "ΤΟΥΣΚΑΛΟΥΣΔΙΕΑΥΤΟΥ", 
            "ΕΥΡΙΣΚΕΙΑΛΛΕΣΤΙΝΟΥΣ", 
            "ΚΑΙΔΙΑΛΛΩΝΚΑΙΤΟΥ", 
            "ΤΟΕΔΗΛΩΣΕΝΟΤΙΑΥ", 
            "ΤΟΣΤΕΣΚΟΠΕΙΚΑΘΟ", 
            "ΣΟΝΕΝΔΕΧΕΤΑΙΚΑΙ", 
            "ΤΟΥΣΑΛΛΟΥΣΕΡΩΤΑ", 
            "ΟΙΣΟΡΑΣΥΜΒΑΛΛΟΝ", 
            "ΤΑΣΤΟΥΣΝΕΟΥΣΚΑΙ", 
            "ΓΑΡΤΟΤΟΙΣΔΕΗΤΟΙΣ", 
            "ΔΕΣΥΝΕ[.]ΝΑΙΜΗΝΥΕΙ", 
            "ΤΟΥΣΕΥΦΥΕ[.]ΣΝΥΝΔΕ", 
            "ΚΑΙΜΗΜΟΙΑΧΘΟΥΟΥ", 
            "ΚΕΣΤΙΝΚΑΛΟΣΠΡΟΣ", 
            "ΕΟΙΚΕΔΕΣΟΙΤΗΝΤΕ", 
            "ΣΙΜΟΤΗΤΑΚΑΙΤΟΕ", 
            "ΞΩΤΩΝΟΜΜΑΤΩΝ", 
            "ΗΤΤΟΝΔΕΗΣΥΤΑΥΤΕ", 
            "ΧΕΙΟΕΟΔΩΡΟΣΤΟΝ", 
            "ΚΑΛΟΝΚΑΤΑΤΑΥΠΟ", 
            "ΤΩ[.]ΠΟΛΛΩΝΝΟΜΙ", 
            "ΖΟΜΕΝΑΤΟΝΕΚΤΗΣ", 
            "ΜΟΡΦΗΣΤΟΙΟΥΤΟΝΟ", 
            "ΜΟΙΩΣΔΕΕΚ[.]ΩΝΑΥ", 
            "ΤΩ[.]ΚΑΙΤΟΝΑ[.]ΣΧΡΟΝ", 
            "ΦΗΣΙΝΤΕΤΟΝΕΑΙ", 
            "ΤΗΤΟΝΕΟΙΚΕΝΑΙΤΩ", 
            "ΩΚΡΑΤΕΙΚΑΤΑΤΕ", 
            "ΤΗΝΣΕΙΜΟΤΗΤΑΚΑΙ", 
            "ΤΟΕΞΩΕΧΕΙΝΤΑ[.]Μ", 
            "ΜΑΤ[.]ΟΥΜΕΝΤ[.]ΙΕΠΙ", 
            "ΣΗΣΤΩΩΚΡ[.]ΤΕΙ", 
            "ΟΔΕΩΚΡΑΤΗ[...]Λ", 
            "ΛΟΝΟ[.]ΔΕΚΑΛΟΝ[...]", 
            "ΚΑΛΩΣΛΕΓΟΝΤΑΤ[..]", 
            "ΤΕΣΤΙ[.]ΤΟ[.]ΦΡΟΝ[....]", 
            "ΩΣΠΡΟΕΛ[.]ΩΝΕΡΕΙ", 
            "ΤΟΓΑ[.]ΕΥΜ[.]ΘΗΟΝΤΑ", 
            "ΩΣΑΛΛΩΧ[.....]Ν", 
            "ΠΡΑΟΝΑΥΕ[.....]ΙΑ", 
            "ΦΕΡΟΝ[.]ΩΣΚ[.....]", 
            "ΤΟΥΤΟΙΣΑΝΔ[.]ΕΙΟΝ", 
            "ΠΑΡΟΝΤΙΝΟΥΝΕΓΩ", 
            "ΜΕΝΟΥΤΑΝΩΟΜΗΝ", 
            "ΓΕΝΕΣΘΑΙΟ[.]ΤΕΟΡΩΓΙΓΝΟΜΕΝΟΝΤΟΕΥΜΑ", 
            "ΘΕΣΚΑΤΑΤΟΛΟΓΙΣΤΙ", 
            "ΚΟΝΤΗΣΨΥΧΗΣΤΟ", 
            "ΠΡΑΟΝΚΑΙΑΝΔΡΕΙΟΝ", 
            "ΚΑΤΑΤΟΘΥΜΟΕΙΔΕΣ", 
            "ΔΟΚΕΙΔΕΤΑΤΟΙΑΥΤΑ", 
            "ΠΑΡΑΠΟΔΙΖΕΙΝΑΛ", 
            "ΛΗΛΟΙΣΕΠΙΓΕΤΩΝΕΥ", 
            "ΦΥΙΩΝΟΥΓΑΡΩΣΠΕΡ", 
            "ΕΠΙΤΩΝΤΕΛΕΙΩΝΑ", 
            "ΡΕΤΩΝΟΥΤΩΣΚΑΙΕ", 
            "ΠΙΤΩΝΕΥΦΥΙΩΝΕ", 
            "ΞΑΝΑΓΚΗΣΗΑΝΤ[.]ΚΟ", 
            "ΛΟΥΘΙΑΑΛΛΑΤΑΠΟΛΛΑ", 
            "ΚΑΙΕΝΑΝΤΙΟΥΝΤΑΙΑΛ", 
            "ΛΗΛΑΙΣΔΙΑΤΟΥΤΟΚΑΙ", 
            "ΦΗΣΙΝΟΕΟΔΩΡΟΣ", 
            "ΟΥΤΕΩΟΜΗΝΓΕΝΕ", 
            "ΣΘΑΙΟΥΤΕΟΡΩΓΙΓΝΟ", 
            "ΜΕΝΟΝΟΥΚΕΙΑΝΕΛΠΙ", 
            "ΣΤΟΝΔΑΥΤΩΚΑΙΟΥΧ[.]", 
            "ΡΑΓΙΓΝΟΜΕΝΟΝΕΥΘΕ", 
            "ΩΣΚΑΙΑΔΥΝΑΤΟΝΤΩ", 
            "ΓΟΥΝΕΑΙΤΗΤΩΜΑΡ", 
            "ΤΥΡΕΙΩΣΕΧΟΝΤΙΤΑΥΤΑ", 
            "ΑΛΛΟΙΤΕΟΞΕΙΣΩΣ[...]", 
            "ΟΥΤΟΣΚΑΙΑΓΧΙΝΟΙΚ[.]Ι", 
            "ΜΝΗΜΟΝΕΣΩΣΤΑ", 
            "ΠΟΛΛΑΚΑΙΠΡΟΣΤΑΣ", 
            "ΟΡΓΑΣΟΞΥΡΡΟΠΟ[.]ΕΙΣΙΝ", 
            "ΚΑΙΑΤΤΟΝΤΕΣΦΕΡΟΝΤΑΙ", 
            "[]ΩΣΠΕΡΤΑΑΝΕΡΜΑΤΙ", 
            "[]ΣΤΑΠΛΟΙΑΚΑΙΜΑΝΙΚ[.]", 
            "ΤΕΡΟΙΗΑΝΔΡΕΙΟΤΕΡΟΙ", 
            "ΦΥΟΝΤΑΙΟΞΥΤΗΣΚΑΙ", 
            "ΑΓΧΙΝΟ[.]ΑΚΑΙΤΟΜΝΗ", 
            "ΜΟΝΙΚ[.]ΝΕΥΦΥΙΑΙ", 
            "ΤΟΥΛΟΓΙΣΤ[.]ΚΟΥΚΑΙΟ", 
            "ΞΥΤΗΣΜ[.]ΝΚΑΤΑΓ", 
            "ΧΙΝΟΙΑΝΚΑΤΑΤΟΡΑ", 
            "ΔΙΩΣΝΟΕΙ[....]ΕΝ", 
            "ΤΡΕΧ[..]ΤΟΔΕΜ[..]", 
            "ΜΟΝΙΚΟΝΚΑΤΑΤΟ[..]Α", 
            "ΤΕΙΝΤΩΝΝΟΗΘΕ[.]", 
            "ΤΩΝΟΙΤΟΙΟΥΤΟΙΟΥΝ", 
            "ΩΣΕΠΙΠΑΝΕΥΚΙΝΗ", 
            "ΤΟΙΕΙΣΙΝΚΑΙΣΕΣΟΒΗ", 
            "ΜΕΝΩΣΟΡΜΩΣΙΝ", 
            "ΩΣΠΕΡΦΕΡΕΤΑΙΤΑΑΝ", 
            "ΕΡΜΑΤΙΣΤΑΠΛΟΙΑΚΟΥ", 
            "ΦΩΣΜΕΝΔΙΑΤΟΜΗ", 
            "ΓΕΓΟΜΩΣΘΑΙΕΙΚΗ", 
            "ΔΕΔΙΑΤΟΜΗΕΧΕΙΝΕΡ", 
            "ΜΑΚΑΙΟΙΤΟΙΟΥΤΟΙΟΥΝ", 
            "ΤΩΝΝΕΩΝΜΑΝΙΚΩ", 
            "ΤΕΡΟΙΗΠΕΡΑΝΔΡΕΙ", 
            "ΟΤΕΡΟΙΦΥΟΝΤΑΙΤΟΓΑΡ"]}]
    }]
}