{ 
        "head": { 
        "tm": "64276",
        "graphicName": "64276__PBerol9917.png",
        "textparts": "1",

        "lines": "27",
        "version": "D4"
            },

        "body": [{
            "textpart": [{
        "n": "11",
        "subtype": "",
        "textpartLines": "27",
        "text": [
"[-]ΑΤΩΝΛΕΓΟΜΕΝΩΝΟΙΟΝ",
"Ε̣Ι̣Σ̣Ι̣ΗΗΕ---[-]--ΣΥΝΔΕΣΜΟΙ",
"ΕΡΩΤΗΜΑΤΙΚΟΙΗΗΕΠΕΡΙΣΠΩ",
"ΤΑΙΜΕΝΟ̣ΤΕΕΙΣΙΝ[--]ΩΤΗΜΑΤΙ",
"ΚΟΙΟΞΥΤΟΝΟΥΝ̣Τ̣ΑΙΟΔΕΕΙΣΙΝ",
"ΔΙΑΞΕΥΚΤΙΚΟ̣ΙΤΟ̣ΔΕΗΠΕΡΙ[-]ΠΩ",
"ΜΕΝΩΣΚΑΙΠΑΡΑΠΛΗΡΩΜΑΤΙ",
"ΚΟΣΣΥΝΔΕΣΜΟΣΕΣΤΙΝΩΣ",
"ΕΝΤΩΕΠΕΙΗΠΟΛΥΦΕΡΤΕΡΟΝ",
"ΕΣΤΙΝΑΠΟΡΗΜΑΤΙΚΟΙΔΕ",
"ΕΙΣΙΝΔΙΩΝΑΠΟΡΟΥΤΕΣ[-]Ο",
"ΛΟΓΟΝΕΚΦΕΡΕΙΝΕΙΩΘΑ",
"ΜΕΝΗΡΑΑΡΑΚΑΤΑΜΩΝΕΙΤΑ",
"ΕΠΕΙΤΑΜΗΠΟΤΕΠΟΤΕΡΑΕΝΙΟ̣[-]",
"ΣΗΔΕ̣ΚΑΙΕ̣ΝΕΠΙΡΡΗΜΑΣΙΧΡΟΝΙ",
"ΚΟ̣Ι̣[-]ΤΑΣΣΕΤΑΙΤΟΕΙ̣Τ̣Α̣ΚΑΙΤΟΕ̣",
"ΠΕΙΤΑΣΥΝΔΕΣΜΟΙΠΑΡΑΠΛΗ",
"ΡΩΜΑΤΙΚΟΙΜΗΔΕ[-]ΙΣΟΔΥΝΑ",
"ΜΟΥΝΤΕΣΤΩΔΗΝ[-]ΘΗΝΑΚΡΑ",
"ΑΡΑΜΗΝΜΑΝΔΗΓ[-]Ρ̣ΠΩ̣ΚΑΙ",
"ΤΑΟΜΟΙΑΣΥΝΔΕΣΜΟΙΠΑΡΑ",
"ΠΛΗΡΩΜΑΤΙΚΟΙΜΗΔΕΝ[-]ΣΟΔΥ",
"ΝΑΜΟΥΝΤΕΣΑΝΓΕΤΟΙΠΩΠΕ[-]",
"ΟΥΝΣΥΝΣΥΝΔΕΣΜΟΙΠ[-]Ρ[----]",
"ΡΩΜΑΤΙΚΟΙΕΑΥ[-]ΟΙΣΙΣΟ[----]",
"ΜΟΥΝΤΕΣΔΗΔΗΘΕΝ[------]",
"ΠΕΡΙΕΠ[--]ΡΗ[-]Α[---]"]}]

        }]
}
