{

"head": {   
    "tm": "62580",
    "side": "1",
    "noRom": "0",
    "part": "C",
    "graphicName": "P_09782-Pl-C_R_001.jpg",
    "textparts": "1",
    "lines": "184",
    "version": "D2"
    },

"body": [
    {
    "textpart": [{
        "n": "11",
        "subtype": "column",
        "textpartLines": "184",
        "text": [
            "Α_ΔΡΕΙΟΝΟΥΚΕΜΠΛΗ", 
            "ΚΤΟΝΑΛΛΑΣΤΑΣΙΜΟΝ", 
            "ΟΙΤΕΑΥΕΜΒΡΙΘΕΣΤΕ", 
            "ΡΟΙΝΩΘΡΟΙΠΩΣΑΠΑΝ", 
            "ΤΩΣΙΝΠΡΟΣΤΑΣΜΑΘΗ", 
            "ΣΕΙΣΚΑΙΛΗΘΗΣΓΕΜΟΝ", 
            "ΤΕΣΟΙΔΕΒΑΡΥΤΕΡΟΙΟΥ", 
            "ΚΕΧΟΝΤΕΣΤΟΟΞΥΑΜ", 
            "ΒΛΥΤΕΡΟΙΕΙΣΙΝΕΝΤΩΙ", 
            "ΜΑΝΘΑΝΕΙΝΚΑΙΕΠΙ", 
            "ΛΗΣΜΟΝΕΣΓΙΝΟΝΤΑΙ", 
            "ΚΑΤΑΜΕΝΟΥΝΤΟΥΣΠΑ", 
            "ΛΑΙΟΥΣΕΠΕΙΠΟΛΛΑΙΑΙ", 
            "ΑΡΕΤΑΙΚΑΙΚΑΤ", 
            "ΕΚΑΣΤΗ ΜΙΑΕΥΦΥΙΑ", 
            "ΖΗΤΗΘΗΣΕΤΑΙΕΙΑΝ", 
            "_ΑΚΟΛΟΥΘΟΥΣΙΑΛ_Η", 
            "ΛΑΙΣΑΙΕΥΦΥΙΑΙ_ _Ο", 
            "ΜΟΛΟΓΕΙΤΑΙΤΟΜΗ_", 
            "ΤΩΣΟΥΜΕΝΤΟΙΑΔΥΝ", 
            "ΤΟΝΤΟΝΜΙΑΝΕΧΟΝ_Α", 
            "ΚΑΙΤΑΣΑΛΛΑΣΕΧΕΙΝ_", 
            "ΤΑΔΕΤΟΥΣΤΩΙΚΟΥΣ", 
            "ΟΥΔΕΖΗΤΕΙΤΑΙΤΟΥΤ_", 
            "ΜΙΑΝΓΕΥΠΟΒΑΛΛΟ_", 
            "ΤΑΣΕΥΦΥΙΑ__ _", 
            "Τ_ΙΣΑΡΕΤΑΙ ΕΙΚ_Ζ _", 
            "_Γ ΡΤΟΗΓ_Ο_ _Ν", 
            "_ΡΩΙΕΥΠ_ _ _ΙΠ_", 
            "_ΚΟΤ_ _Ν Ε", 
            "ΧΕΣΘΑΙ_ _Ο", 
            "ΘΕΝΟΥΔ Α", 
            "ΕΡΩΤΑΑ_ __", 
            "ΟΣΕΙΜΙΑ_ _Υ", 
            "ΙΑΜΙΑΕ_ Ν_ Α_Ε", 
            "ΤΗΑΛ_ _ΝΜΙΑΕΣ", 
            "ΤΙΝΕΥΦ_Ι_ΩΣΟΜΟ", 
            "ΛΟΓΟΥΣΙΠΡΟΣΟΥΣΟΛΟ", 
            "ΓΟΣΜΙΑΑΡΑΕΣΤΙΝΑΡΕ", 
            "ΤΗΟΔΕΟΥΤΩΣΛΕΙΩΣ", 
            "ΤΕΚΑΙΑΠΤΑΙΣΤΩΣΚΑΙ", 
            "ΑΝΥΣΙΜΩΣΕΡΧΕΤΑΙ", 
            "ΕΠΙΤΑΣΜΑΘΗΣΕΙΣΤΕ", 
            "ΚΑΙΖΗΤΗΣΕΙΣΜΕΤΑ", 
            "ΠΟΛΛΗΣΠΡΑΙΟΤ_ΤΟΣ", 
            "ΟΙΟΝΕΛΑΙΟΥ_ΜΑ_", 
            "ΨΟΦΗΤΙΡΕΟΝΤΟΣΟΙ", 
            "ΟΝΔΕΙΕΙΝΑΙΕΝΤΑ_ΖΗ", 
            "ΤΗΣΕΣΙ_ΑΙΜΑΘΗΣΕΣΙ", 
            "ΥΠΟΓΡ_ΦΕΙΟΤΙΔΕΙΛΕΙ", 
            "ΩΣΠΡΟΙΝΑΙΤΟ_ΤΕ", 
            "ΣΤΙΝ__ΙΑΠ ΔΩΝ", 
            "ΤΑΑ_ΣΤΩΣΜΗ", 
            "ΠΡ_Κ_ΥΟΝΤ ΑΑ_Υ", 
            "ΣΙ__Ε_ΝΑΚΑΙ_ΡΟ", 
            "Κ_ΤΗΙΔΕΙΔΕΠΡΟΣ", 
            "ΕΙ_ΑΙ_ _ΤΗΝΠΡΑΟ", 
            "ΤΗΤΑΚ_ΜΗΑΓΡΙΑΙ", 
            "ΝΕΙΝΩ_Π_ΡΚΑΙΤΟΕ", 
            "ΛΑΙΟΝ_ΕΙΑΨΟΦΗΤΙ", 
            "ΩΣΤΕΘΑΥΜΑΣΑΙΤΟ", 
            "ΤΗΛΙΚΟΥΤΟΝΟΝΤΑΟΥ", 
            "ΤΩΣΤΑ_ΤΑΔΙΑΠΡΑΤΤΕ", 
            "ΣΘΑΙΤΟΤΗΛΙΚΟΥΤΟΝ", 
            "ΑΝΤΙΤ_ΥΝΕΟΝΟΝΤΑ", 
            "ΘΑΥΜΑ_ΤΟΝΟΥΝΕΙΚΑΙ", 
            "ΕΝ_ΟΥ_ΩΤΗΣΗΛΙΚΙ", 
            "ΑΣΕΜΜΕΛΩΣΖΗΤΕΙ", 
            "ΕΥΑΓ_ΕΙΣΥΦΕΝΑΝΑ", 
            "ΓΝΩΣΤΕΟΝΕΞΑΚΟΥ", 
            "ΕΤΑΙ__ΑΛΑΑΓΓΕΛ", 
            "_ΙΣΕΑΙΤΗΤΟΣΩ", 
            "_ ΡΑ_ΕΣΤΟΓΕΟ_", 
            "ΟΥ ΕΝΟΝΟΜΑ", 
            "_ΟΣΟΥΚ", 
            "ΟΔΩΡΟ__", 
            "_ΑΙΤΗ_ _", 
            "ΦΟ_", 
            "ΤΟΙΟ_", 
            "ΜΟΙΕ_", 
            "Σ_ΕΦ", 
            "_Ο_", 
            "_ΡΟ _Τ _ _", 
            "Μ_Τ_ ΛΕ_ΕΡ Ο_", 
            "Τ_ΘΑ _Σ_ΟΣΩΩ", 
            "_ΑΤ_ _ΝΝΙΚΟΝΛΕ", 
            "_ΙΣΤ_ _Ν_ΡΑΕΠΙ", 
            "ΤΗΔΕ _ΝΗΣΘΗΤΟΥ", 
            "ΠΑΤΡ_ ΚΑ_ΤΗΣΔΙΑ", 
            "ΦΘΟΡΑ__ΩΝΧΡΗΜΑ", 
            "ΤΩΝ_ΗΣΥΠΟΤΩΝΕ", 
            "_ _Ρ_ ΩΝ_ΝΑΔΕΙ", 
            "_ _ ΕΛ_ΥΘΕ _ΟΝ", 
            "_ Ν_Η ΩΣ_Ε_ΝΙ", 
            "ΚΟΝΕΝΓΑ_ΤΟΙΣΜΑΛΙ", 
            "ΣΤΑΚΑΙΤΟΥΤΟΣ_ΟΠΕΙΕΙ", 
            "ΕΛΕΥΘΕΡΙΟΣΕΣ_ΙΝΟ", 
            "ΝΕΟΣΗΟΥΩΣΤΗΣΑΝΕ", 
            "ΛΕΥΘΕΡΙΟΤΗΤΟΣΙΚΑ", 
            "ΝΗΣΟΥΣΗΣΛΥΜΗΝΑ", 
            "ΣΘΑ__ΑΟΘ_ΝΚΑΝ", 
            "ΤΗΙΟΛ_ ΕΙ__Ο", 
            "ΠΩΝΤΟΥ_Ε_Φ_ΕΙΣ", 
            "Κ_ _ΗΦΗΣ_ _ _ΜΗ", 
            "_Ε ΘΗΙΑΝΕ ΘΕ", 
            "ΡΙΟ_ΣΠΡΟΣΟ ΣΑ", 
            "ΕΙΜΕΝΑΡΑΗΜ_ ΤΟΥ", 
            "ΣΩ_ΑΤΟΣΤΙΟΜΟΙΟΥΣ", 
            "_ΗΣΙΝΕΙΝΑΙΕΠΑΙ", 
            "Ν _ΗΨΕΓΩ_ΟΥ", 
            "_ΝΥ_ΤΩΙΑΞ_ΟΝ", 
            "_ _ΥΝΠΡ_ _ΧΕΙΝ", 
            "Ε_ ΟΕΟΔ_ΟΣ", 
            "Τ_Ν_ ΤΗΤΟ _ΩΙ", 
            "Ω_ ΤΕΙΕ_ Κ_ΝΑΙ", 
            "ΚΑ_Α_ΕΤΗΝΣ_ΜΟ", 
            "Τ_ΚΑΙΤΟΕΞ_ΤΩΝ", 
            "ΟΜ_ ΩΝΚΑΤ__ΟΥ", 
            "ΤΟ_ _Σ_ΑΥ_Ν", 
            "ΕΙ_ ΙΣ_", 
            "Δ", 
            "_", 
            "ΤΕ_", 
            "ΠΡΟ", 
            "ΤΟ", 
            "_", 
            "_ ΙΟ", 
            "_ _ _", 
            "_ _ ΡΟΥ", 
            "_ Ν ΗΝ_", 
            "_ Ι_ _ _", 
            "ΤΕ_ΑΙ _Ν_Ο_ΚΑ", 
            "_ΙΟΝ _ΕΝ_ΚΟΥ", 
            "ΣΑ_ _ΘΥ_ _ΣΘ_", 
            "ΑΝΑ_ΚΕ_ΑΣΘ _", 
            "ΕΠΑΙΝΕΘ_Ν_ _ΙΔ", 
            "ΠΡΟΘΥΜ Σ_ _", 
            "ΕΠΙΔΕΙΚ _Ν _Μ_", 
            "ΛΟΓΗΘΗΑ _ΤΑ", 
            "ΕΚΑ_ΤΟΝ ΚΑΝΟΝΕΙΝΑΙ", 
            "ΑΠ ΦΑΙΝΕΣΘΑΙΑΠΕΡ", 
            "ΚΑ__ΠΕΙΡΟΣΕΣΤΙΝ", 
            "ΤΟ_Δ_ΕΟΔΩΡΟΝ", 
            "ΕΝΤΟΙΣΜΑΘΗΜΑΣΙΕΙ", 
            "ΝΑ Ι_ΑΝΩΤΑΤΟΝΕΠΕΙ", 
            "ΟΥ_ΟΤΟΙΟΥΤΟΣΕΠ", 
            "ΝΕ_ ΗΝΨΥΧΗΝΤ _ΟΣ", 
            "ΟΥ_ _ΔΙΑΨΕΥΣΘΕΙ_", 
            "ΔΙΑ_ΟΥΤΟΑ_ _ΝΣΠΟΥ", 
            "ΔΑΣ_ΤΩ _ΝΑΚΟΥ", 
            "ΣΑΝ_ ΣΚ_ΨΑΣΘΑΙΤΟΝ", 
            "ΕΠΑΙ_ΕΘΕ_ΑΑΡΑΓΕ", 
            "ΤΟΙΟ _ΟΣ_ΤΙΝΗΟΥ", 
            "ΤΩΙ_ Ε_ ΕΘΕΝ", 
            "ΤΙ_ Θ_ΣΠΑΡΕ", 
            "_ _Υ_ _ΤΑΣ", 
            "ΘΗ_ _Α _Α", 
            "ΜΗ _Υ _ΜΟ", 
            "ΛΟΓ_ _ΝΑ _ΤΟ", 
            "ΜΕ_ _ΑΙΖ _ΑΛΕ", 
            "ΓΕΙΝ_ ΝΔΕΕΠ_ΙΩ", 
            "ΜΟΛ_ _ΣΕ_Ο ΕΠΕΙ", 
            "ΠΕ ΔΕΥ_ _ΟΔ_", 
            "ΠΑΙΝ", 
            "ΨΥ", 
            "_ΙΕ_ΥΤ_", 
            "_ ΕΙΤ_", 
            "_ _Ε_", 
            "Ε_", 
            "_", 
            "_", 
            "ΚΑΙΟΡ", 
            "_ΩΝΕΛΕΓ", 
            "ΚΝΥΕΙΟ_", 
            "ΩΣΑΥΤΟΥ_ Α _", 
            "__ΙΟΥ_ Τ Ε", 
            "ΝΟΝ_ΣΤ __", 
            "Γ_Μ_ ΟΙΣ_ _Τ_", 
            "_ _ΕΙ__ΑΥΤ Ι", 
            "_ ΝΑΙΜΑΝ_Α", 
            "_ΟΥΠΑΡΑΕΟΔΩ", 
            "Γ_ΩΜΕΤΡΙΑΣΑ_Τ", 
            "ΟΥ ΕΙΠΕΝΜΑΝΘΑ_", 
            "_ _ΔΩΡΟΥΓ_"]}]
    }]
}