{

"head": {   
    "tm": "63976",
    "side": "1",
    "noRom": "0",
    "part": "0",
    "graphicName": "P_21213_R.jpg",
    "textparts": "1",
    "lines": "22",
    "version": "N4"
    },

"body": [
    {
    "textpart": [{
        "n": "1",
        "subtype": "fragment",
        "textpartLines": "22",
        "text": [
            "[.]", 
            "[.][..][.]", 
            "[.][.]ολο[.]δω[.]", 
            "[.]στησα[.][.]ω[.]", 
            "[.....]ωκρα[..]καὶ ἐκστήσ[.....]", 
            "[......]ποσοντῆς φυσικ[....]", 
            "[........]πρώτης υστήσασθα[......]", 
            "[.....]νἧς ἐφήνατοπολυφων[.....]", 
            "[......]ςπροεπέφαντοὧνἕκαστος ἀπὸ[]", 
            "[.........]ικεχειρημένων προέστη", 
            "[......]νέβη τὰς αἱρέσεις κτισθῆναι", 
            "[.......]Κυνικὴν Μεγαρικὴν Ἐρετρι", 
            "[........]ε[.]πενοὐδὲν[..]δηνε[...]", 
            "[.][..]λονκ[.]ταλογάδη[.]τοῦ ου", 
            "[.][..]νοι[.]ι πολὺ γὰρ", 
            "[.]τιἐβού[..]το αὐτοῦ τὰ ἀπο", 
            "[.][...][.][...]τ[.]", 
            "[.][...][.]τωνι", 
            "[.][..][.][.]χινη", 
            "[.][...]", 
            "[.][..]", 
            "[.]"]}]
    }]
}